AutoFeatureEnginerring/__init__.py
AutoFeatureEnginerring/auto_eng.py
AutoFeatureEnginerring/logger.py
auto_fe-0.0.2.dist-info/LICENSE
auto_fe-0.0.2.dist-info/METADATA
auto_fe-0.0.2.dist-info/WHEEL
auto_fe-0.0.2.dist-info/top_level.txt
auto_fe-0.0.2.dist-info/RECORD
